logbox/__init__.py
logbox/_api.py
logbox/_channels.py
logbox/_codes.py
logbox/_iterators.py
logbox/_logger.py
logbox/_progbars.py
logbox/_timeformat.py
logbox/params.yml
logbox/_cli/__init__.py
logbox/_cli/_bypass.py
logbox/_cli/_windows.cp38-win_amd64.pyd
logbox/printer/__init__.py
logbox/printer/__main__.py
logbox-1.1.1.dist-info/LICENSE
logbox-1.1.1.dist-info/METADATA
logbox-1.1.1.dist-info/WHEEL
logbox-1.1.1.dist-info/top_level.txt
logbox-1.1.1.dist-info/RECORD
