Metadata-Version: 2.1
Name: logbox
Version: 1.1.1
Summary: Toolbox for terminal output and logging to file
Author: Matthias Nadig
Author-email: nadig_develop@yahoo.com
License: MIT
License-File: LICENSE
Requires-Dist: PyYAML
